kpredict/__init__.py
kpredict/kpredict.py
kpredict/classes/__init__.py
kpredict/classes/config.py
kpredict/classes/models.py
kpredict/data/__init__.py
kpredict/data/tristate_options_413.json
kpredict/data/tristate_options_415.json
kpredict/data/tristate_options_420.json
kpredict/data/tristate_options_500.json
kpredict/data/tristate_options_504.json
kpredict/data/tristate_options_507.json
kpredict/data/tristate_options_508.json
kpredict/exceptions/__init__.py
kpredict/exceptions/exceptions.py
kpredict/helpers/__init__.py
kpredict/helpers/helpers.py
kpredict/models/__init__.py
kpredict/models/model_413.joblib
kpredict/models/model_415.joblib
kpredict/models/model_420.joblib
kpredict/models/model_500.joblib
kpredict/models/model_504.joblib
kpredict/models/model_507.joblib
kpredict/models/model_508.joblib
kpredict-0.1.1.data/scripts/kpredict
kpredict-0.1.1.dist-info/LICENSE
kpredict-0.1.1.dist-info/METADATA
kpredict-0.1.1.dist-info/WHEEL
kpredict-0.1.1.dist-info/top_level.txt
kpredict-0.1.1.dist-info/RECORD
