Metadata-Version: 2.1
Name: kpredict
Version: 0.1.1
Summary: UNKNOWN
Home-page: https://github.com/HugoJPMartin/kpredict
Author: Hugo Martin
Author-email: hugo.martin@irisa.fr
License: UNKNOWN
Platform: UNKNOWN
Requires-Python: >=3.8
Requires-Dist: scikit-learn (==0.23.0)
Requires-Dist: numpy (>=1.16.2)
Requires-Dist: pandas
Requires-Dist: joblib
